{"2010":"","2016":"","Department":"Верховний Суд України","Region":"Загальнодержавний","Position":"Суддя Верховного Суду України.","Name":"Гриців Михайло Іванович","Link":"https://drive.google.com/open?id=0BygiyWAl79DMWTdKN1VxX1M4ZjA","Note":"У меня","AdditionalNote":"","декларації 2015":"","Youtube":"","ПІБ2":"","Кількість справ":"","Оскаржені":"","Кількість скарг":"","Кількість дисциплінарних стягнень":"","Клейма":6,"Фото":"http://picua.org/img/2016-11/05/p4ukbck232qdcal2pn5326h4z.jpg","Як живе":"","Декларація доброчесності судді подано у 2016 році (вперше)":"http://vkksu.gov.ua/userfiles/declaracii-suddiv/vs/grytsiv.PDF","Декларація родинних зв’язків судді подано у 2016 році":"http://vkksu.gov.ua/userfiles/declaracii-suddiv/vs/grytsivrz.PDF","key":"griciv_mihaylo_ivanovich","analytics":[{"y":2016,"m":180000,"i":428840,"c":1,"k":213.5,"ka":8,"fi":643557,"fc":1,"ff":53.5,"ffa":1,"fh":100.2,"fha":2,"fl":12545,"fla":3},{"y":2015,"m":150000,"i":311422,"c":1,"k":53.38,"ka":2,"fi":382509,"fc":1,"ff":213.63,"ffa":3,"fh":100.2,"fha":2,"fl":12545,"fla":3},{"y":2015,"m":150000,"i":311422,"c":1,"k":53.38,"ka":2,"fi":382509,"fc":1,"ff":213.63,"ffa":3,"fh":100.2,"fha":2,"fl":12545,"fla":3},{"y":2014,"i":334263,"c":1,"k":211,"ka":2,"la":5,"fi":386458,"ff":211,"ffa":2},{"y":2013,"b":115776,"i":411367,"c":1,"k":256,"ka":3,"fi":343462,"ff":211,"ffa":2}],"declarationsLinks":[{"id":"572165e6-b922-4ae3-8998-603db2f5d57b","year":2016,"provider":"public-api.nazk.gov.ua"},{"id":"9405ef71-8f44-4a56-84bc-0ee92206942e","year":2015,"provider":"public-api.nazk.gov.ua"},{"id":"ab2b0d98-f14e-4064-830b-774508d81474","year":2015,"provider":"public-api.nazk.gov.ua"},{"id":"vulyk_56_169","year":2014,"url":"http://static.declarations.com.ua/declarations/chosen_ones/mega_batch/hrytsiv_mykhailo_ivanovych.pdf","provider":"declarations.com.ua"},{"id":"vulyk_70_19","year":2013,"url":"http://static.declarations.com.ua/declarations/chosen_ones/judges_batch/19_hrytsiv_mykhailo_ivanovych.pdf","provider":"declarations.com.ua"}]}