{"2010":"","2016":"","Department":"Господарський суд м. Києв","Region":"м. Київ","Position":"Суддя Господарського суду м. Києва","Name":"Гусєва Тетяна Олексіївна","Link":"https://drive.google.com/open?id=0BygiyWAl79DMZV9LYUg3bEo5d28","Note":"У меня","AdditionalNote":"","field8":"","field9":"","ПІБ2":"","Кількість справ":"","Оскаржені":"","Кількість скарг":0,"Кількість дисциплінарних стягнень":"","Клейма":4,"Фото":"","Як живе":"","Декларація доброчесності судді подано у 2016 році (вперше)":"","Декларація родинних зв’язків судді подано у 2016 році":"","key":"gusieva_tetyana_oleksiyivna","analytics":[{"y":2016,"i":13841,"c":1,"k":213.4,"ka":2,"h":60.4,"ha":1,"l":434,"la":1,"fc":1,"ff":65,"ffa":1},{"y":2014,"i":41507,"c":1,"k":213.4,"ka":2,"h":60.4,"ha":1,"l":434,"la":1,"ff":65,"ffa":1}]}