{"2010":"","2016":"","Department":"Господарський суд Львівської області","Region":"Львівська область","Position":"Суддя Господарського суду Львівської області","Name":"Щигельська Олена Ігорівна","Link":"https://drive.google.com/open?id=0BygiyWAl79DMQ2dteUhSdUVKX28","Note":"У меня","AdditionalNote":"","декларації 2015":"","Youtube":"","ПІБ2":"","Кількість справ":"","Оскаржені":"","Кількість скарг":"2","Кількість дисциплінарних стягнень":"","Клейма":"","Фото":"","Як живе":"","Декларація доброчесності судді подано у 2016 році (вперше)":"","Декларація родинних зв’язків судді подано у 2016 році":"","key":"shchigelska_olena_igorivna","field8":"","Link 2015":"","field9":"","Декларації 2013":"","Декларації 2014":"","Декларації 2015":"","Декларації 2016":"","type":"judge","analytics":[{"y":2014,"i":181736.04,"c":1,"k":139.2,"ka":2},{"y":2015,"b":5829,"i":167164,"c":1,"k":34.9,"ka":1,"ff":69.4,"ffa":1,"j":2},{"y":2016,"b":402,"m":698583.19,"i":214406,"c":1,"k":34.9,"ka":1,"l":1131,"la":1,"ff":69.4,"ffa":1},{"y":2017,"m":675123.31,"i":227223,"c":1,"k":34.9,"ka":1,"l":1131,"la":1,"ff":69.4,"ffa":1}],"declarationsLinks":[{"id":"vulyk_94_79","year":2014,"url":"https://declarations.com.ua/declaration/vulyk_94_79","provider":"declarations.com.ua.opendata"},{"id":"nacp_8682b9df-6dbe-4b4a-84d4-5da0ac518d33","year":2015,"url":"https://declarations.com.ua/declaration/nacp_8682b9df-6dbe-4b4a-84d4-5da0ac518d33","provider":"declarations.com.ua.opendata"},{"id":"nacp_aacdb990-97ec-40ac-8bae-d1465ee6059c","year":2016,"url":"https://declarations.com.ua/declaration/nacp_aacdb990-97ec-40ac-8bae-d1465ee6059c","provider":"declarations.com.ua.opendata"},{"id":"nacp_ec22a878-e1f3-4332-8843-1c414d08272f","year":2017,"url":"https://declarations.com.ua/declaration/nacp_ec22a878-e1f3-4332-8843-1c414d08272f","provider":"declarations.com.ua.opendata"}]}