{"ft_src":"Skoda,Octavia\n229357\n2013\n481\n48,95\n31.50\n31,5\n62,6\n30000\nFALSE\nFALSE\nFALSE\n2013\n324432\n212976\n325488\n353617\n128000\n1032\n24\n24\n229357\nSkoda,Octavia\n2013\nFALSE\nFALSE\n481\n31.50\n31,5\n48,95\n62,6\nСуддя Донецького Апеляційного Адміністративного суду\nДружина - Потоцька С.С.;донька - Чумак М.С;\nЧумак\nЧумак Сергій Юрійович\nСергій Юрійович Чумак\nСергій Чумак\nЧумак Сергій Юрійович\nСергій\nЧумак Сергій Юрійович\nАпеляційний адміністративний суд\nСуддя\nДонецька область\nЮрійович\n5920\n2050\n212976\n324432\n24\n24\n353617\n325488\n128000\n1032\n30000\n2013\nFALSE\n5920\n2050\nЧумак\nЮрійович\nДружина - Потоцька С.С.;донька - Чумак М.С;\nЧумак Сергій Юрійович\nСергій Юрійович Чумак\nСергій Чумак\nЧумак Сергій Юрійович\nСергій\nСуддя Донецького Апеляційного Адміністративного суду\nСуддя\nДонецька область\nАпеляційний адміністративний суд\nЧумак Сергій Юрійович","estate":{"23":[{"costs":"","address":"","space_units":"","costs_rent_comment":"","space":"481","costs_comment":"","costs_rent":"","space_comment":"","region":"","location_raw":""},{"costs":"","address":"","space_units":"","costs_rent_comment":"","space":"","costs_comment":"","costs_rent":"","space_comment":"","region":"","location_raw":""},{"costs":"","address":"","space_units":"","costs_rent_comment":"","space":"","costs_comment":"","costs_rent":"","space_comment":"","region":"","location_raw":""}],"24":[{"costs":"","address":"","space_units":"","costs_rent_comment":"","space":"31,5","costs_comment":"","costs_rent":"","space_comment":"","region":"","location_raw":"31.50"}],"25":[{"costs":"","address":"","space_units":"","costs_rent_comment":"","space":"62,6","costs_comment":"","costs_rent":"","space_comment":"","region":"","location_raw":""}],"31":[{"costs_property_comment":"","address":"","space_units":"","costs_rent_comment":"","space":"48,95","space_comment":"","costs_property":"","region":"","location_raw":"","costs_rent":""}]},"vehicle":{"35":[{"sum_comment":"","brand_info":"","sum":"229357","sum_rent_comment":"","year":"2013","brand":"Skoda,Octavia","sum_rent":"","brand_hidden":false}]},"id":"5675","income":{"5":{"family_comment":"","value":"353617","family":"325488","comment":""},"6":{"family_comment":"","value":"212976","family":"324432","comment":""},"7":{"family":"0","family_comment":"","value":"0","comment":"","source_name":"0"},"8":{"family_comment":"","value":"0","family":"0","comment":""},"9":{"family_comment":"","value":"0","family":"1032","comment":""},"10":{"family_comment":"","value":"0","family":"0","comment":""},"11":{"family_comment":"","value":"0","family":"0","comment":""},"12":{"family_comment":"","value":"0","family":"0","comment":""},"13":{"family_comment":"","value":"0","family":"0","comment":""},"14":{"family_comment":"","value":"0","family":"0","comment":""},"15":{"family_comment":"","value":"0","family":"0","comment":""},"16":{"family_comment":"","value":"128000","family":"0","comment":""},"17":{"family_comment":"","value":"0","family":"0","comment":""},"18":{"family_comment":"","value":"0","family":"0","comment":""},"19":{"family_comment":"","value":"0","family":"0","comment":""},"20":{"family_comment":"","value":"24","family":"24","comment":""},"21":[{"country_comment":"","uah_equal":"0","country":"0","cur":"0"},{"country_comment":"","uah_equal":"0","country":"0","cur":"0"},{"country_comment":"","uah_equal":"0","country":"0","cur":"0"},{"country_comment":"","uah_equal":"0","country":"0","cur":"0"},{"country_comment":"","uah_equal":"0","country":"0","cur":"0"}],"22":[{"country_comment":"","uah_equal":"0","country":"0","cur":"0"},{"country_comment":"","uah_equal":"0","country":"0","cur":"0"},{"country_comment":"","uah_equal":"0","country":"0","cur":"0"},{"country_comment":"","uah_equal":"0","country":"0","cur":"0"},{"country_comment":"","uah_equal":"0","country":"0","cur":"0"}]},"banks":{"45":[{"sum_units":"UAH","sum_comment":"","sum_foreign_units":"","sum":"","sum_foreign_comment":"","sum_foreign":""},{"sum_units":"USD","sum_comment":"","sum_foreign_units":"","sum":"","sum_foreign_comment":"","sum_foreign":""},{"sum_units":"EUR","sum_comment":"","sum_foreign_units":"","sum":"","sum_foreign_comment":"","sum_foreign":""}],"46":[{"sum_units":"UAH","sum_comment":"","sum_foreign_units":"","sum":"","sum_foreign_comment":"","sum_foreign":""},{"sum_units":"USD","sum_comment":"","sum_foreign_units":"","sum":"","sum_foreign_comment":"","sum_foreign":""},{"sum_units":"EUR","sum_comment":"","sum_foreign_units":"","sum":"","sum_foreign_comment":"","sum_foreign":""}],"47":[{"sum_units":"","sum_comment":"","sum_foreign_units":"","sum":"","sum_foreign_comment":"","sum_foreign":""}],"48":[{"sum_units":"","sum_comment":"","sum_foreign_units":"","sum":"","sum_foreign_comment":"","sum_foreign":""}],"49":[{"sum_units":"","sum_comment":"","sum_foreign_units":"","sum":"","sum_foreign_comment":"","sum_foreign":""}],"50":[{"sum_units":"","sum_comment":"","sum_foreign_units":"","sum":"","sum_foreign_comment":"","sum_foreign":""}],"51":[{"sum_units":"UAH","sum_comment":"","sum_foreign_units":"","sum":"30000","sum_foreign_comment":"","sum_foreign":""},{"sum_units":"USD","sum_comment":"","sum_foreign_units":"","sum":"","sum_foreign_comment":"","sum_foreign":""},{"sum_units":"EUR","sum_comment":"","sum_foreign_units":"","sum":"","sum_foreign_comment":"","sum_foreign":""}],"52":[{"sum_units":"","sum_comment":"","sum_foreign_units":"","sum":"","sum_foreign_comment":"","sum_foreign":""}],"53":[{"sum_units":"","sum_comment":"","sum_foreign_units":"","sum":"","sum_foreign_comment":"","sum_foreign":""}]},"declaration":{"notfull_lostpages":"","additional_info_text":"","additional_info":"FALSE","notfull":"FALSE","url":"http://static.declarations.com.ua/declarations/sudy/apeliatsiini_administratyvni_sudy/donetskyi/chumak.pdf","needs_scancopy_check":false},"general":{"family_raw":"Дружина - Потоцька С.С.;донька - Чумак М.С;","name":"Сергій","full_name_suggest":{"input":["Чумак Сергій Юрійович","Сергій Юрійович Чумак","Сергій Чумак"],"output":"Чумак Сергій Юрійович"},"post_raw":"Суддя Донецького Апеляційного Адміністративного суду","name_unclear":false,"patronymic":"Юрійович","patronymic_unclear":false,"last_name_hidden":false,"patronymic_hidden":false,"inn":"","addresses_raw_hidden":true,"last_name":"Чумак","full_name":"Чумак Сергій Юрійович","post":{"office":"Апеляційний адміністративний суд","region":"Донецька область","post":"Суддя"},"addresses_raw":"","name_hidden":false,"last_name_unclear":false},"liabilities":{"54":{"sum_comment":"","sum_foreign_comment":"","sum_foreign":"","sum":""},"55":{"sum_units":"","sum_comment":"","sum_foreign_units":"","sum":"","sum_foreign_comment":"","sum_foreign":""},"56":{"sum_comment":"","sum_foreign_comment":"","sum_foreign":"","sum":"5920"},"57":{"sum_comment":"","sum_foreign_comment":"","sum_foreign":"","sum":""},"58":{"sum_comment":"","sum_foreign_comment":"","sum_foreign":"","sum":""},"59":{"sum_comment":"","sum_foreign_comment":"","sum_foreign":"","sum":""},"60":{"sum_comment":"","sum_foreign_comment":"","sum_foreign":"","sum":""},"61":{"sum_units":"","sum_comment":"","sum_foreign_units":"","sum":"","sum_foreign_comment":"","sum_foreign":""},"62":{"sum_comment":"","sum_foreign_comment":"","sum_foreign":"","sum":"2050"},"63":{"sum_comment":"","sum_units":"","sum_foreign":"","sum":"","sum_foreign_comment":""},"64":{"sum_comment":"","sum_units":"","sum_foreign":"","sum":"","sum_foreign_comment":""}},"intro":{"isnotdeclaration":"FALSE","declaration_year":"2013"}}