[{"declaration":{"date":"2016-03-31T00:00:00","additional_info":"","url":"http://static.declarations.com.ua/declarations/chosen_ones/judges_batch/1956_kryvokhyzha_vira_ivanivna_2015.pdf","additional_info_text":""},"liabilities":{"54":{"sum_unclear":false,"sum_comment_hidden":false,"sum_hidden":false,"sum_foreign_hidden":false,"sum_foreign":"","sum_foreign_comment":"","sum":"1461","sum_comment":""},"55":{"sum_foreign":"","sum_foreign_comment":"","sum":"","sum_comment":""},"56":{"sum_foreign":"","sum_foreign_comment":"","sum":"5251","sum_comment":"","sum_unclear":false},"57":{"sum_comment_hidden":false,"sum_foreign":"","sum_foreign_hidden":false,"sum_comment_unclear":false,"sum_foreign_comment":"","sum":"31051","sum_comment":""},"58":{"sum_unclear":false,"sum_foreign_comment":"","sum":"42138","sum_comment":"","sum_foreign":""},"59":{"sum_foreign":"","sum_foreign_comment":"","sum":"","sum_comment":""},"60":{"sum_comment_hidden":false,"sum_foreign":"","sum_foreign_hidden":false,"sum_foreign_comment":"","sum":"","sum_comment":""},"61":{"sum_foreign":"","sum_foreign_comment":"","sum":"","sum_comment":""},"62":{"sum_foreign":"","sum_foreign_comment":"","sum":"","sum_comment":""},"63":{"sum_foreign":"","sum_foreign_comment":"","sum":"","sum_comment":""},"64":{"sum_foreign":"","sum_foreign_comment":"","sum":"","sum_comment":""}},"general":{"family_raw":"","inn":"","inn_hidden":true,"patronymic":"Іванівна","last_name":"Кривохижа","name":"Віра","post":{"post":"суддя апеляційного суду кіровоградської області","region_unclear":false,"office_unclear":false,"region":"Кіровоградська область","office":"Загальний апеляційний суд"},"full_name":"Кривохижа Віра Іванівна","addresses":[{"place_city_hidden":true,"place":"","place_city_type":"","place_hidden":true,"place_address_hidden":true,"place_district":"","place_city":"","place_city_type_hidden":false,"place_district_hidden":false,"place_address":""}],"full_name_suggest":{"output":"Кривохижа Віра Іванівна","input":["Кривохижа Віра Іванівна","Віра Іванівна Кривохижа","Віра Кривохижа"]}},"source":"VULYK","intro":{"isnotdeclaration":"","declaration_year":"2015"},"banks":{"45":[{"sum_hidden":false,"sum_comment_hidden":false,"sum_foreign":"","sum_unclear":false,"sum_foreign_units":"UAH","sum_foreign_hidden":false,"sum_foreign_comment":"","sum_units":"UAH","sum":"59","sum_comment":""}]},"income":{"5":{"family_comment":"","value":"284554","family":"","comment":""},"6":{"comment":"","value":"257229","value_unclear":false,"family_comment":"","family":""},"7":{"comment":"","source_name_hidden":false,"source_name":"","family_comment":"","value":"","family":""},"8":{"family_comment":"","value":"","family":"","comment":""},"9":{"family_comment":"","value":"1925","family":"","comment":""},"10":{"family_comment":"","value":"13398","family":"","comment":""},"11":{"comment_hidden":false,"family_comment":"","value":"","family":"","comment":""},"12":{"family_comment":"","value":"","family":"","comment":""},"13":{"family_comment":"","value":"","family":"","comment":""},"14":{"family_comment":"","value":"","family":"","comment":""},"15":{"comment":"","family_unclear":false,"value_unclear":false,"family_comment":"","value":"","family":""},"16":{"family_comment":"","value":"","family":"","comment":""},"17":{"family_comment":"","value":"","family":"","comment":""},"18":{"family_comment":"","value":"","family":"","comment":""},"19":{"family_comment":"","value":"","family":"","comment":""},"20":{"family_comment":"","value":"12002","family":"","comment_unclear":false,"comment":"пенсія"}},"estate":{"24":[{"costs":"","space_units":"м²","space":"111.8","address":"","region":"","space_comment_unclear":false,"space_comment":"іпотека, кредит","costs_rent_comment":"","costs_rent":"","space_hidden":false,"costs_comment":"","address_hidden":false,"region_hidden":true}]},"id":"vulyk_104_158"},{"declaration":{"additional_info":"","additional_info_text":"","date":"2015-03-27T00:00:00","notfull_lostpages":"","url":"http://static.declarations.com.ua/declarations/chosen_ones/judges_batch/2298_kryvokhyzha_vira_ivanivna.pdf","notfull":""},"liabilities":{"54":{"sum_foreign":"","sum_foreign_comment":"","sum":"","sum_comment":""},"55":{"sum_foreign":"","sum_foreign_comment":"","sum":"","sum_comment":""},"56":{"sum_foreign":"","sum_foreign_comment":"","sum":"5346","sum_comment":""},"57":{"sum_foreign":"","sum_foreign_comment":"","sum":"48345","sum_comment":""},"58":{"sum_foreign":"","sum_foreign_comment":"","sum":"27148","sum_comment":""},"59":{"sum_foreign":"","sum_foreign_comment":"","sum":"","sum_comment":""},"60":{"sum_foreign":"","sum_foreign_comment":"","sum":"","sum_comment":""},"61":{"sum_foreign":"","sum_foreign_comment":"","sum":"","sum_comment":""},"62":{"sum_foreign":"","sum_foreign_comment":"","sum":"","sum_comment":""},"63":{"sum_foreign":"","sum_foreign_comment":"","sum":"","sum_comment":""},"64":{"sum_foreign":"","sum_foreign_comment":"","sum":"","sum_comment":""}},"source":"VULYK","intro":{"declaration_year":"2014"},"estate":{"24":[{"costs":"","space_units":"м²","space":"111.8","address":"","region":"","space_comment":"іпотека","costs_rent_comment":"","costs_rent":"","space_hidden":false,"costs_comment":"","address_hidden":false,"region_hidden":false}],"25":[{"costs":"","space_units":"м²","space":"45","address":"","region":"","space_comment_unclear":false,"space_comment":"","costs_rent_comment":"","region_unclear":false,"costs_rent":"","space_unclear":false,"space_hidden":false,"costs_comment":"","address_hidden":false,"region_hidden":true}]},"income":{"5":{"comment":"","value":"274104","family":"","family_comment":""},"6":{"comment_hidden":false,"comment":"","family_comment_hidden":false,"family_comment":"","value":"260706","family":""},"7":{"comment":"","source_name":"","family_comment":"","value":"","comment_unclear":false,"family":""},"8":{"comment":"","value":"","family":"","family_comment":""},"9":{"comment":"","value":"","family":"","family_comment":""},"10":{"family_comment":"","value":"13398","family":"","family_hidden":false,"comment":""},"11":{"comment":"","value":"","family":"","family_comment":""},"12":{"family_comment":"","value":"","family":"","comment":""},"13":{"family_comment":"","value":"","comment":"","family":""},"14":{"comment":"","value":"","family":"","family_comment":""},"15":{"comment":"","value":"","family":"","family_comment":""},"16":{"family_comment":"","value":"","comment":"","family":""},"17":{"family_comment":"","value":"","comment":"","family":""},"18":{"family_comment":"","value":"","family":"","comment":""},"19":{"comment":"","value":"","family":"","family_comment":""},"20":{"comment":"пенсія","value_unclear":false,"family_comment":"","value":"71120","family_hidden":false,"family":""}},"general":{"inn":"","patronymic":"Іванівна","last_name":"Кривохижа","name":"Віра","full_name_suggest":{"output":"Кривохижа Віра Іванівна","input":["Кривохижа Віра Іванівна","Віра Іванівна Кривохижа","Віра Кривохижа"]},"family":[{"name_unclear":true,"inn":"","inn_hidden":false,"family_name":"Глуговська Марина Анатоліївна","relations_other":"","name_hidden":false,"relations":"Дитина","relations_hidden":false}],"family_raw":"","post":{"post_unclear":false,"post":"суддя апеляційного суду кіровоградської області","office":"Загальний апеляційний суд","office_unclear":false,"candidate":"","region":"Кіровоградська область"},"inn_hidden":true,"last_name_unclear":false,"inn_unclear":false,"full_name":"Кривохижа Віра Іванівна","addresses":[{"place_city":"","place_address_unclear":false,"place_city_unclear":false,"place_address":"","place_city_type_hidden":false,"place_hidden":true,"place":"","place_district":"","place_city_hidden":false,"place_city_type":"","place_address_hidden":false,"place_city_type_unclear":false,"place_district_hidden":false}]},"id":"vulyk_83_28"},{"declaration":{"additional_info":"FALSE","needs_scancopy_check":false,"additional_info_text":"","notfull_lostpages":"","url":"http://unshred.it/static/declarations/sudy/apeliatsiini_sudy_oblastei__m.kyieva/kirovohradska/kryvohyzha.pdf","notfull":"FALSE"},"liabilities":{"54":{"sum_foreign":"","sum_foreign_comment":"","sum":"","sum_comment":""},"55":{"sum_foreign_units":"","sum_foreign":"","sum_foreign_comment":"","sum_units":"","sum":"","sum_comment":""},"56":{"sum_foreign":"","sum_foreign_comment":"","sum":"4785","sum_comment":""},"57":{"sum_foreign":"","sum_foreign_comment":"","sum":"42186","sum_comment":""},"58":{"sum_foreign":"","sum_foreign_comment":"","sum":"22958","sum_comment":""},"59":{"sum_foreign":"","sum_foreign_comment":"","sum":"","sum_comment":""},"60":{"sum_foreign":"","sum_foreign_comment":"","sum":"","sum_comment":""},"61":{"sum_foreign_units":"","sum_foreign":"","sum_foreign_comment":"","sum_units":"","sum":"","sum_comment":""},"62":{"sum_foreign":"","sum_foreign_comment":"","sum":"","sum_comment":""},"63":{"sum_foreign":"","sum_foreign_comment":"","sum_units":"","sum":"","sum_comment":""},"64":{"sum_foreign":"","sum_foreign_comment":"","sum_units":"","sum":"","sum_comment":""}},"estate":{"23":[{"space_units":"","costs_rent_comment":"","costs":"","location_raw":"","space_comment":"","space":"","costs_comment":"","address":"","region":"","costs_rent":""},{"space_units":"","costs_rent_comment":"","costs":"","location_raw":"","space_comment":"","space":"","costs_comment":"","address":"","region":"","costs_rent":""},{"space_units":"","costs_rent_comment":"","costs":"","location_raw":"","space_comment":"","space":"","costs_comment":"","address":"","region":"","costs_rent":""}],"24":[{"space_units":"","costs_rent_comment":"","costs":"","location_raw":"приховано","space_comment":"","space":"111,8","costs_comment":"","address":"","region":"","costs_rent":""}],"25":[{"space_units":"","costs_rent_comment":"","costs":"","location_raw":"приховано","space_comment":"","space":"45","costs_comment":"","address":"","region":"","costs_rent":""}]},"income":{"5":{"comment":"","value":"256931","family_comment":"","family":"0"},"6":{"comment":"","value":"244314","family_comment":"","family":"0"},"7":{"source_name":"0","comment":"","value":"0","family_comment":"","family":"0"},"8":{"comment":"","value":"0","family_comment":"","family":"0"},"9":{"comment":"","value":"0","family_comment":"","family":"0"},"10":{"comment":"","value":"12617","family_comment":"","family":"0"},"11":{"comment":"","value":"0","family_comment":"","family":"0"},"12":{"comment":"","value":"0","family_comment":"","family":"0"},"13":{"comment":"","value":"0","family_comment":"","family":"0"},"14":{"comment":"","value":"0","family_comment":"","family":"0"},"15":{"comment":"","value":"0","family_comment":"","family":"0"},"16":{"comment":"","value":"0","family_comment":"","family":"0"},"17":{"comment":"","value":"0","family_comment":"","family":"0"},"18":{"comment":"","value":"0","family_comment":"","family":"0"},"19":{"comment":"","value":"0","family_comment":"","family":"0"},"20":{"comment":"","value":"65929","family_comment":"","family":"0"},"21":[{"country":"0","uah_equal":"0","country_comment":"","cur":"0"},{"country":"0","uah_equal":"0","country_comment":"","cur":"0"},{"country":"0","uah_equal":"0","country_comment":"","cur":"0"},{"country":"0","uah_equal":"0","country_comment":"","cur":"0"},{"country":"0","uah_equal":"0","country_comment":"","cur":"0"}],"22":[{"country":"0","uah_equal":"0","country_comment":"","cur":"0"},{"country":"0","uah_equal":"0","country_comment":"","cur":"0"},{"country":"0","uah_equal":"0","country_comment":"","cur":"0"},{"country":"0","uah_equal":"0","country_comment":"","cur":"0"},{"country":"0","uah_equal":"0","country_comment":"","cur":"0"}]},"banks":{"45":[{"sum_foreign_units":"","sum_foreign":"","sum_foreign_comment":"","sum_units":"UAH","sum":"","sum_comment":""},{"sum_foreign_units":"","sum_foreign":"","sum_foreign_comment":"","sum_units":"USD","sum":"","sum_comment":""},{"sum_foreign_units":"","sum_foreign":"","sum_foreign_comment":"","sum_units":"EUR","sum":"","sum_comment":""}],"46":[{"sum_foreign_units":"","sum_foreign":"","sum_foreign_comment":"","sum_units":"UAH","sum":"","sum_comment":""},{"sum_foreign_units":"","sum_foreign":"","sum_foreign_comment":"","sum_units":"USD","sum":"","sum_comment":""},{"sum_foreign_units":"","sum_foreign":"","sum_foreign_comment":"","sum_units":"EUR","sum":"","sum_comment":""}],"47":[{"sum_foreign_units":"","sum_foreign":"","sum_foreign_comment":"","sum_units":"","sum":"","sum_comment":""}],"48":[{"sum_foreign_units":"","sum_foreign":"","sum_foreign_comment":"","sum_units":"","sum":"","sum_comment":""}],"49":[{"sum_foreign_units":"","sum_foreign":"","sum_foreign_comment":"","sum_units":"","sum":"","sum_comment":""}],"50":[{"sum_foreign_units":"","sum_foreign":"","sum_foreign_comment":"","sum_units":"","sum":"","sum_comment":""}],"51":[{"sum_foreign_units":"","sum_foreign":"","sum_foreign_comment":"","sum_units":"UAH","sum":"","sum_comment":""},{"sum_foreign_units":"","sum_foreign":"","sum_foreign_comment":"","sum_units":"USD","sum":"","sum_comment":""},{"sum_foreign_units":"","sum_foreign":"","sum_foreign_comment":"","sum_units":"EUR","sum":"","sum_comment":""}],"52":[{"sum_foreign_units":"","sum_foreign":"","sum_foreign_comment":"","sum_units":"","sum":"","sum_comment":""}],"53":[{"sum_foreign_units":"","sum_foreign":"","sum_foreign_comment":"","sum_units":"","sum":"","sum_comment":""}]},"intro":{"isnotdeclaration":"FALSE","declaration_year":"2013"},"general":{"inn":"","patronymic_hidden":false,"patronymic":"Іванівна","last_name":"Кривохижа","name":"Віра","patronymic_unclear":false,"post_raw":"Суддя апеляційного суду Кіровоградської області","addresses_raw":"приховано","addresses_raw_hidden":true,"full_name_suggest":{"output":"Кривохижа Віра Іванівна","input":["Кривохижа Віра Іванівна","Віра Іванівна Кривохижа","Віра Кривохижа"]},"family_raw":"Донька Глуговська Марина Анатоліївна, 8 липня 1994 року народження","post":{"post":"Суддя","region":"Кіровоградська область","office":"Загальний апеляційний суд"},"last_name_hidden":false,"full_name":"Кривохижа Віра Іванівна","name_hidden":false,"name_unclear":false,"last_name_unclear":false},"id":"4715"}]