{"banks":{"45":[{"sum_units_unclear":false,"sum":"33532","sum_foreign":"","sum_foreign_comment":"","sum_comment_hidden":true,"sum_comment":"","sum_hidden":false,"sum_units_hidden":false,"sum_foreign_units":"UAH","sum_units":"UAH","sum_unclear":false}],"46":[{"sum":"33532","sum_unclear":false,"sum_foreign_comment":"","sum_comment_hidden":true,"sum_foreign":"","sum_comment":"","sum_foreign_units":"UAH","sum_units":"UAH"}],"51":[{"sum":"8585","sum_unclear":false,"sum_foreign_comment":"","sum_comment_hidden":true,"sum_hidden":false,"sum_comment":"","sum_foreign_units":"UAH","sum_foreign":"","sum_units":"UAH"}],"53":[{"sum":"38","sum_foreign":"","sum_foreign_comment":"","sum_comment_hidden":true,"sum_comment":"","sum_foreign_units":"UAH","sum_units":"UAH"}]},"declaration":{"notfull":"","additional_info":"","url":"http://static.declarations.com.ua/declarations/chosen_ones/judges_batch/3656_losiev_anton_mykhailovych.pdf","date":"2015-03-26T00:00:00","notfull_lostpages":"","additional_info_text":""},"estate":{"29":[{"address_hidden":false,"space":"1270","costs_rent":"","space_units":"м²","costs_property":"","costs_rent_comment":"","space_comment":"","costs_property_comment":"","address":"","region":"","region_hidden":true}],"30":[{"address_hidden":false,"space":"310","costs_rent":"","space_hidden":false,"space_units":"м²","region":"","region_hidden":true,"costs_property_comment":"","space_comment":"","costs_property":"","costs_rent_comment":"","address":""}]},"general":{"family_raw":"","name":"Антон","family":[{"name_unclear":false,"relations_hidden":false,"name_hidden":true,"inn":"","inn_hidden":true,"family_name":"","relations":"Подружжя"},{"name_unclear":false,"relations_unclear":false,"relations_other":"","name_hidden":true,"inn":"","inn_hidden":true,"family_name":"","relations":"Дитина"},{"name_unclear":false,"relations_unclear":false,"relations_other":"","name_hidden":true,"inn":"","inn_hidden":true,"family_name":"","relations":"Дитина"}],"full_name":"Лосєв Антон Михайлович","full_name_suggest":{"input":["Лосєв Антон Михайлович","Антон Михайлович Лосєв","Антон Лосєв"]},"patronymic":"Михайлович","patronymic_hidden":false,"addresses":[{"place_city_hidden":true,"place_district":"","place_city_type_hidden":true,"place_hidden":true,"place_address_hidden":true,"place_city":"","place_address":"","place_district_hidden":true,"place_city_type":"","place":""}],"inn_unclear":false,"inn":"","inn_hidden":true,"last_name":"Лосєв","post":{"post_unclear":false,"candidate":"","office":"Вищий адміністративний суд України","post_hidden":false,"office_unclear":false,"post":"суддя вищого адміністративного суду україни","region_unclear":false,"region":"Загальнодержавний регіон"}},"id":"vulyk_94_10","income":{"5":{"family_comment":"","family":"1213708","value_unclear":false,"comment":"","family_hidden":false,"value":"240881"},"6":{"family_comment":"","value_unclear":false,"comment":"","value":"225232","family":""},"7":{"family_comment":"","value":"","source_name_unclear":false,"family":"","source_name":"","comment":"","source_name_hidden":false},"8":{"family_comment":"","comment":"","value":"","family":""},"9":{"family_comment":"","comment":"проценти","comment_unclear":false,"value":"884","family":""},"10":{"family_comment":"","comment":"","value":"14616","family":""},"11":{"family_comment":"","comment":"","family_unclear":false,"value":"125","family":""},"12":{"family_comment":"","comment":"","value":"","family":""},"13":{"family_comment":"","comment":"","value":"","family":""},"14":{"family_comment":"","comment":"","value":"","family":""},"15":{"family_comment":"","comment":"","value":"","family":""},"16":{"family_comment":"","comment":"","value":"","family":""},"17":{"family_comment":"","comment":"","value":"","family":"1203700"},"18":{"family_comment":"","comment":"","value":"","family":""},"19":{"family_comment":"","comment":"","value":"","family":""},"20":{"family_comment":"","comment_unclear":false,"family":"10008","value_unclear":false,"comment":"новорічний дитячий подарунок","value":"24"}},"intro":{"isnotdeclaration":"","declaration_year":"2014"},"liabilities":{"54":{"sum":"","sum_foreign":"","sum_foreign_comment":"","sum_comment_hidden":false,"sum_comment":"","sum_comment_unclear":false,"sum_unclear":false},"55":{"sum":"","sum_comment":"","sum_foreign":"","sum_foreign_comment":""},"56":{"sum":"","sum_foreign":"","sum_comment":"","sum_unclear":false,"sum_foreign_comment":""},"57":{"sum":"","sum_unclear":false,"sum_foreign_comment":"","sum_hidden":false,"sum_comment":"","sum_foreign":""},"58":{"sum":"","sum_unclear":false,"sum_foreign_comment":"","sum_hidden":false,"sum_comment":"","sum_foreign":""},"59":{"sum":"","sum_comment":"","sum_foreign":"","sum_foreign_comment":""},"60":{"sum":"","sum_comment":"","sum_foreign":"","sum_foreign_comment":"","sum_comment_hidden":false},"61":{"sum":"","sum_comment":"","sum_foreign":"","sum_foreign_comment":""},"62":{"sum":"","sum_hidden":false,"sum_comment":"","sum_foreign":"","sum_foreign_comment":""},"63":{"sum":"","sum_comment":"","sum_foreign":"","sum_foreign_comment":"","sum_comment_hidden":false},"64":{"sum":"","sum_foreign":"","sum_comment":"","sum_unclear":false,"sum_foreign_comment":""}},"source":"VULYK","vehicle":{"35":[{"brand_info":"4999 куб. см.","brand_unclear":false,"brand_info_hidden":false,"year_unclear":false,"brand":"Land Rover Range Rover","brand_info_unclear":false,"year_hidden":false,"sum":"","sum_rent":"","brand_hidden":false,"sum_comment":"","sum_rent_comment":"","year":"2012"}],"40":[{"sum":"","brand_info_hidden":false,"brand_info":"2996 куб. см.","sum_rent_comment":"","year":"2008","sum_rent":"","sum_comment":"","brand_hidden":false,"brand_unclear":false,"brand_info_unclear":false,"brand":"BMW X5"},{"sum":"","brand_info":"2993 куб. см.","sum_rent_comment":"","sum_rent":"","sum_comment":"","year":"2013","brand_info_unclear":false,"brand":"Land Rover Range Rover"}]}}